pytest_diff_selector/__init__.py
pytest_diff_selector/main.py
pytest_diff_selector/plugin.py
pytest_diff_selector-0.1.3.dist-info/LICENSE
pytest_diff_selector-0.1.3.dist-info/METADATA
pytest_diff_selector-0.1.3.dist-info/WHEEL
pytest_diff_selector-0.1.3.dist-info/entry_points.txt
pytest_diff_selector-0.1.3.dist-info/top_level.txt
pytest_diff_selector-0.1.3.dist-info/RECORD
