Metadata-Version: 2.1
Name: pytest-diff-selector
Version: 0.1.3
Summary: Get tests affected by code changes (using git)
Home-page: https://github.com/fruch/pytest-diff-selector
Author: Israel Fruchter
Author-email: israel.fruchter@gmail.com,
License: MIT
Project-URL: Source, https://github.com/fruch/pytest-diff-selector
Project-URL: Tracker, https://github.com/fruch/pytest-diff-selector/issues
Keywords: pytest,git
Platform: UNKNOWN
Classifier: Development Status :: 4 - Beta
Classifier: Environment :: Console
Classifier: Framework :: Pytest
Classifier: Intended Audience :: Developers
Classifier: Topic :: Software Development :: Testing
Classifier: License :: OSI Approved :: MIT License
Classifier: Programming Language :: Python :: 3.7
Classifier: Programming Language :: Python :: 3.8
Classifier: Programming Language :: Python :: 3.9
Classifier: Programming Language :: Python :: 3.10
Classifier: Programming Language :: Python :: 3 :: Only
Classifier: Programming Language :: Python :: Implementation :: CPython
Classifier: Operating System :: OS Independent
Requires-Python: >=3.7
License-File: LICENSE
Requires-Dist: unidiff
Requires-Dist: pyan3 (==1.2.0)
Requires-Dist: tqdm
Provides-Extra: all
Requires-Dist: pytest (>=6.2.2) ; extra == 'all'
Requires-Dist: pytest-git ; extra == 'all'
Requires-Dist: pre-commit ; extra == 'all'
Requires-Dist: pytest-cov ; extra == 'all'
Provides-Extra: test
Requires-Dist: pytest (>=6.2.2) ; extra == 'test'
Requires-Dist: pytest-git ; extra == 'test'
Requires-Dist: pre-commit ; extra == 'test'
Requires-Dist: pytest-cov ; extra == 'test'
